LICENSE
MANIFEST.in
README.md
README.rst
setup.py
google_site_verification/__init__.py
google_site_verification/tests.py
google_site_verification/urls.py
google_site_verification/views.py
google_site_verification.egg-info/PKG-INFO
google_site_verification.egg-info/SOURCES.txt
google_site_verification.egg-info/dependency_links.txt
google_site_verification.egg-info/top_level.txt
google_site_verification/templates/google_site_verification/google_verification.html