Metadata-Version: 1.1
Name: google-site-verification
Version: 0.0.4
Summary: django-google-site-verification
Home-page: https://github.com/lotrekagency/django-google-site-verification
Author: Lotrek
Author-email: dimmitutto@lotrek.it
License: MIT
Platform: UNKNOWN
Classifier: Environment :: Web Environment
Classifier: Framework :: Django
Classifier: Intended Audience :: Developers
Classifier: Programming Language :: Python
Classifier: Programming Language :: Python :: 3
